gradedoc/__init__.py
gradedoc/__main__.py
gradedoc/add_template_comments.py
gradedoc/cli.py
gradedoc/close_all.py
gradedoc/configs.py
gradedoc/copy_example.py
gradedoc/deductions_to_semicolon_separated_variables.py
gradedoc/delete_all_comments.py
gradedoc/open_all.py
gradedoc/save_all.py
gradedoc/shared.py
gradedoc/toggle_active_review_pane.py
gradedoc/update_active_grade.py
gradedoc/update_all_grades.py
gradedoc/update_grade.py
gradedoc/example/config.yaml
gradedoc/example/config_lab_specific.yaml
gradedoc/example/toggle_active_review_pane.ahk
gradedoc/example/update_active_grade.ahk
gradedoc-0.0.10.dist-info/entry_points.txt
gradedoc-0.0.10.dist-info/LICENSE
gradedoc-0.0.10.dist-info/WHEEL
gradedoc-0.0.10.dist-info/METADATA
gradedoc-0.0.10.dist-info/RECORD
