Metadata-Version: 2.1
Name: gradedoc
Version: 0.0.10
Summary: Grader for DOCX lab reports using comments.
Author-email: Blake Naccarato <blake.naccarato+gradedoc@gmail.com>
Requires-Python: >=3.10
Requires-Dist: docxrev~=0.2.4
Requires-Dist: dynaconf~=3.1.9
Requires-Dist: fire~=0.4.0
Requires-Dist: natsort~=8.2.0
Requires-Dist: rich~=12.5.1
Project-URL: Home, https://github.com/blakeNaccarato/gradedoc
